ccyy_demo/__init__.py
ccyy_demo/main.py
ccyy_demo-0.1.1.dist-info/WHEEL
ccyy_demo-0.1.1.dist-info/entry_points.txt
ccyy_demo-0.1.1.dist-info/METADATA
ccyy_demo-0.1.1.dist-info/RECORD
