Metadata-Version: 2.3
Name: ccyy-demo
Version: 0.1.1
Summary: Add your description here
Author: CJ
Author-email: CJ <550056383@qq.com>
Requires-Dist: ruff ; extra == 'dev'
Requires-Dist: mypy ; extra == 'dev'
Requires-Python: >=3.11
Provides-Extra: dev
